lucenequery/ElasticsearchGrammarLexer.py
lucenequery/ElasticsearchGrammarListener.py
lucenequery/ElasticsearchGrammarParser.py
lucenequery/StandardLuceneGrammarLexer.py
lucenequery/StandardLuceneGrammarListener.py
lucenequery/StandardLuceneGrammarParser.py
lucenequery/__init__.py
lucenequery/dialects.py
lucenequery/prefixfields.py
lucenequery-0.1.dist-info/DESCRIPTION.rst
lucenequery-0.1.dist-info/METADATA
lucenequery-0.1.dist-info/RECORD
lucenequery-0.1.dist-info/WHEEL
lucenequery-0.1.dist-info/metadata.json
lucenequery-0.1.dist-info/top_level.txt
