Metadata-Version: 2.0
Name: lucenequery
Version: 0.1
Summary: Parse queries in Lucene and Elasticsearch syntaxes
Home-page: http://github.com/lrowe/lucenequery
Author: Laurence Rowe
Author-email: laurence@lrowe.co.uk
License: Apache
Platform: UNKNOWN
Classifier: Intended Audience :: Developers
Classifier: Programming Language :: Python
Classifier: Programming Language :: Python :: 2.7
Classifier: Programming Language :: Python :: 3
Classifier: Programming Language :: Python :: 3.3
Classifier: Programming Language :: Python :: 3.4
Classifier: Programming Language :: Python :: 3.5
Classifier: Programming Language :: Python :: Implementation :: CPython
Classifier: Programming Language :: Python :: Implementation :: PyPy
Classifier: License :: OSI Approved :: Apache Software License
Requires-Dist: antlr4-python2-runtime; python_version<"3.0"
Requires-Dist: antlr4-python3-runtime; python_version>="3.0"
